pyrngx/__init__.py
pyrngx/_pyrngx.cp313-win_amd64.pyd
pyrngx/_version.py
pyrngx/rng.py
pyrngx-0.1.1.dist-info/METADATA
pyrngx-0.1.1.dist-info/WHEEL
pyrngx-0.1.1.dist-info/RECORD
