Metadata-Version: 2.2
Name: pyrngx
Version: 0.1.1
Summary: Parallel & reproducible counter-based RNG streams for HPC (Philox/Threefry) with stream splitting, jump-ahead and deterministic distributions.
Author: Kabir Dhruw
License: MIT
Requires-Python: >=3.9
Requires-Dist: numpy>=1.22
